{
  "dataset_revision": "a29202f0da409034d651614d87cd8938d254e2ea",
  "task_name": "Vidore2BioMedicalLecturesRetrieval",
  "mteb_version": "2.3.10",
  "scores": {
    "test": [
      {
        "ndcg_at_1": 0.6,
        "ndcg_at_3": 0.61011,
        "ndcg_at_5": 0.62812,
        "ndcg_at_10": 0.66423,
        "ndcg_at_20": 0.69243,
        "ndcg_at_100": 0.72232,
        "ndcg_at_1000": 0.73667,
        "map_at_1": 0.36278,
        "map_at_3": 0.49927,
        "map_at_5": 0.53899,
        "map_at_10": 0.57408,
        "map_at_20": 0.59145,
        "map_at_100": 0.60276,
        "map_at_1000": 0.60425,
        "recall_at_1": 0.36278,
        "recall_at_3": 0.56921,
        "recall_at_5": 0.65428,
        "recall_at_10": 0.76262,
        "recall_at_20": 0.8381,
        "recall_at_100": 0.92801,
        "recall_at_1000": 1.0,
        "accuracy": 0.36278,
        "precision_at_1": 0.6,
        "precision_at_3": 0.37917,
        "precision_at_5": 0.2875,
        "precision_at_10": 0.18375,
        "precision_at_20": 0.11063,
        "precision_at_100": 0.02838,
        "precision_at_1000": 0.00322,
        "mrr_at_1": 0.6,
        "mrr_at_3": 0.686458,
        "mrr_at_5": 0.704896,
        "mrr_at_10": 0.713375,
        "mrr_at_20": 0.715561,
        "mrr_at_100": 0.71573,
        "mrr_at_1000": 0.715871,
        "nauc_ndcg_at_1_max": 0.264665,
        "nauc_ndcg_at_1_std": 0.022707,
        "nauc_ndcg_at_1_diff1": 0.477822,
        "nauc_ndcg_at_3_max": 0.310477,
        "nauc_ndcg_at_3_std": 0.0686,
        "nauc_ndcg_at_3_diff1": 0.375456,
        "nauc_ndcg_at_5_max": 0.327396,
        "nauc_ndcg_at_5_std": 0.061415,
        "nauc_ndcg_at_5_diff1": 0.378649,
        "nauc_ndcg_at_10_max": 0.363505,
        "nauc_ndcg_at_10_std": 0.098995,
        "nauc_ndcg_at_10_diff1": 0.38683,
        "nauc_ndcg_at_20_max": 0.34361,
        "nauc_ndcg_at_20_std": 0.097312,
        "nauc_ndcg_at_20_diff1": 0.36258,
        "nauc_ndcg_at_100_max": 0.339684,
        "nauc_ndcg_at_100_std": 0.104037,
        "nauc_ndcg_at_100_diff1": 0.336313,
        "nauc_ndcg_at_1000_max": 0.314219,
        "nauc_ndcg_at_1000_std": 0.066628,
        "nauc_ndcg_at_1000_diff1": 0.347089,
        "nauc_map_at_1_max": 0.299853,
        "nauc_map_at_1_std": 0.031546,
        "nauc_map_at_1_diff1": 0.576282,
        "nauc_map_at_3_max": 0.309715,
        "nauc_map_at_3_std": 0.044162,
        "nauc_map_at_3_diff1": 0.468343,
        "nauc_map_at_5_max": 0.316004,
        "nauc_map_at_5_std": 0.03876,
        "nauc_map_at_5_diff1": 0.437965,
        "nauc_map_at_10_max": 0.323663,
        "nauc_map_at_10_std": 0.052643,
        "nauc_map_at_10_diff1": 0.419416,
        "nauc_map_at_20_max": 0.321855,
        "nauc_map_at_20_std": 0.055158,
        "nauc_map_at_20_diff1": 0.406065,
        "nauc_map_at_100_max": 0.320497,
        "nauc_map_at_100_std": 0.053943,
        "nauc_map_at_100_diff1": 0.398517,
        "nauc_map_at_1000_max": 0.318236,
        "nauc_map_at_1000_std": 0.051041,
        "nauc_map_at_1000_diff1": 0.398008,
        "nauc_recall_at_1_max": 0.299853,
        "nauc_recall_at_1_std": 0.031546,
        "nauc_recall_at_1_diff1": 0.576282,
        "nauc_recall_at_3_max": 0.304894,
        "nauc_recall_at_3_std": 0.068204,
        "nauc_recall_at_3_diff1": 0.386613,
        "nauc_recall_at_5_max": 0.304004,
        "nauc_recall_at_5_std": 0.048089,
        "nauc_recall_at_5_diff1": 0.302924,
        "nauc_recall_at_10_max": 0.440693,
        "nauc_recall_at_10_std": 0.227508,
        "nauc_recall_at_10_diff1": 0.274882,
        "nauc_recall_at_20_max": 0.38414,
        "nauc_recall_at_20_std": 0.251888,
        "nauc_recall_at_20_diff1": 0.16518,
        "nauc_recall_at_100_max": 0.589484,
        "nauc_recall_at_100_std": 0.617579,
        "nauc_recall_at_100_diff1": -0.081017,
        "nauc_recall_at_1000_max": NaN,
        "nauc_recall_at_1000_std": NaN,
        "nauc_recall_at_1000_diff1": NaN,
        "nauc_precision_at_1_max": 0.264665,
        "nauc_precision_at_1_std": 0.022707,
        "nauc_precision_at_1_diff1": 0.477822,
        "nauc_precision_at_3_max": 0.096188,
        "nauc_precision_at_3_std": 0.063334,
        "nauc_precision_at_3_diff1": -0.100832,
        "nauc_precision_at_5_max": 0.007115,
        "nauc_precision_at_5_std": -0.009432,
        "nauc_precision_at_5_diff1": -0.241161,
        "nauc_precision_at_10_max": -0.023904,
        "nauc_precision_at_10_std": 0.000145,
        "nauc_precision_at_10_diff1": -0.296971,
        "nauc_precision_at_20_max": -0.07458,
        "nauc_precision_at_20_std": -0.002444,
        "nauc_precision_at_20_diff1": -0.342346,
        "nauc_precision_at_100_max": -0.159136,
        "nauc_precision_at_100_std": -0.050409,
        "nauc_precision_at_100_diff1": -0.388572,
        "nauc_precision_at_1000_max": -0.246345,
        "nauc_precision_at_1000_std": -0.135003,
        "nauc_precision_at_1000_diff1": -0.409094,
        "nauc_mrr_at_1_max": 0.264665,
        "nauc_mrr_at_1_std": 0.022707,
        "nauc_mrr_at_1_diff1": 0.477822,
        "nauc_mrr_at_3_max": 0.327712,
        "nauc_mrr_at_3_std": 0.110579,
        "nauc_mrr_at_3_diff1": 0.407181,
        "nauc_mrr_at_5_max": 0.320042,
        "nauc_mrr_at_5_std": 0.088407,
        "nauc_mrr_at_5_diff1": 0.396322,
        "nauc_mrr_at_10_max": 0.325101,
        "nauc_mrr_at_10_std": 0.097125,
        "nauc_mrr_at_10_diff1": 0.403288,
        "nauc_mrr_at_20_max": 0.320072,
        "nauc_mrr_at_20_std": 0.094144,
        "nauc_mrr_at_20_diff1": 0.403585,
        "nauc_mrr_at_100_max": 0.319782,
        "nauc_mrr_at_100_std": 0.094335,
        "nauc_mrr_at_100_diff1": 0.403355,
        "nauc_mrr_at_1000_max": 0.319659,
        "nauc_mrr_at_1000_std": 0.093906,
        "nauc_mrr_at_1000_diff1": 0.404239,
        "cv_recall_at_1": 0.6,
        "cv_recall_at_3": 0.79375,
        "cv_recall_at_5": 0.875,
        "cv_recall_at_10": 0.9375,
        "cv_recall_at_20": 0.96875,
        "cv_recall_at_100": 0.975,
        "cv_recall_at_1000": 1.0,
        "main_score": 0.62812,
        "hf_subset": "french",
        "languages": [
          "fra-Latn"
        ]
      },
      {
        "ndcg_at_1": 0.61875,
        "ndcg_at_3": 0.62627,
        "ndcg_at_5": 0.6489,
        "ndcg_at_10": 0.67018,
        "ndcg_at_20": 0.69947,
        "ndcg_at_100": 0.733,
        "ndcg_at_1000": 0.74525,
        "map_at_1": 0.36944,
        "map_at_3": 0.50624,
        "map_at_5": 0.55258,
        "map_at_10": 0.58148,
        "map_at_20": 0.59887,
        "map_at_100": 0.61122,
        "map_at_1000": 0.61252,
        "recall_at_1": 0.36944,
        "recall_at_3": 0.57936,
        "recall_at_5": 0.67607,
        "recall_at_10": 0.75163,
        "recall_at_20": 0.83632,
        "recall_at_100": 0.94103,
        "recall_at_1000": 1.0,
        "accuracy": 0.36944,
        "precision_at_1": 0.61875,
        "precision_at_3": 0.39167,
        "precision_at_5": 0.3025,
        "precision_at_10": 0.18375,
        "precision_at_20": 0.10969,
        "precision_at_100": 0.02856,
        "precision_at_1000": 0.00322,
        "mrr_at_1": 0.61875,
        "mrr_at_3": 0.713542,
        "mrr_at_5": 0.728854,
        "mrr_at_10": 0.732455,
        "mrr_at_20": 0.734961,
        "mrr_at_100": 0.735387,
        "mrr_at_1000": 0.735481,
        "nauc_ndcg_at_1_max": 0.309381,
        "nauc_ndcg_at_1_std": 0.145117,
        "nauc_ndcg_at_1_diff1": 0.456541,
        "nauc_ndcg_at_3_max": 0.299947,
        "nauc_ndcg_at_3_std": 0.077312,
        "nauc_ndcg_at_3_diff1": 0.388574,
        "nauc_ndcg_at_5_max": 0.308124,
        "nauc_ndcg_at_5_std": 0.067407,
        "nauc_ndcg_at_5_diff1": 0.403899,
        "nauc_ndcg_at_10_max": 0.340812,
        "nauc_ndcg_at_10_std": 0.097004,
        "nauc_ndcg_at_10_diff1": 0.409922,
        "nauc_ndcg_at_20_max": 0.328021,
        "nauc_ndcg_at_20_std": 0.111992,
        "nauc_ndcg_at_20_diff1": 0.391277,
        "nauc_ndcg_at_100_max": 0.324308,
        "nauc_ndcg_at_100_std": 0.128569,
        "nauc_ndcg_at_100_diff1": 0.365334,
        "nauc_ndcg_at_1000_max": 0.300319,
        "nauc_ndcg_at_1000_std": 0.095151,
        "nauc_ndcg_at_1000_diff1": 0.376039,
        "nauc_map_at_1_max": 0.3297,
        "nauc_map_at_1_std": 0.09429,
        "nauc_map_at_1_diff1": 0.576413,
        "nauc_map_at_3_max": 0.314342,
        "nauc_map_at_3_std": 0.075727,
        "nauc_map_at_3_diff1": 0.475938,
        "nauc_map_at_5_max": 0.304516,
        "nauc_map_at_5_std": 0.056651,
        "nauc_map_at_5_diff1": 0.457963,
        "nauc_map_at_10_max": 0.307683,
        "nauc_map_at_10_std": 0.06553,
        "nauc_map_at_10_diff1": 0.442772,
        "nauc_map_at_20_max": 0.305793,
        "nauc_map_at_20_std": 0.071564,
        "nauc_map_at_20_diff1": 0.431069,
        "nauc_map_at_100_max": 0.306642,
        "nauc_map_at_100_std": 0.074561,
        "nauc_map_at_100_diff1": 0.422875,
        "nauc_map_at_1000_max": 0.304243,
        "nauc_map_at_1000_std": 0.072015,
        "nauc_map_at_1000_diff1": 0.422713,
        "nauc_recall_at_1_max": 0.3297,
        "nauc_recall_at_1_std": 0.09429,
        "nauc_recall_at_1_diff1": 0.576413,
        "nauc_recall_at_3_max": 0.3218,
        "nauc_recall_at_3_std": 0.066276,
        "nauc_recall_at_3_diff1": 0.41707,
        "nauc_recall_at_5_max": 0.298408,
        "nauc_recall_at_5_std": 0.032758,
        "nauc_recall_at_5_diff1": 0.357837,
        "nauc_recall_at_10_max": 0.371885,
        "nauc_recall_at_10_std": 0.111567,
        "nauc_recall_at_10_diff1": 0.315121,
        "nauc_recall_at_20_max": 0.351464,
        "nauc_recall_at_20_std": 0.192985,
        "nauc_recall_at_20_diff1": 0.225286,
        "nauc_recall_at_100_max": 0.549169,
        "nauc_recall_at_100_std": 0.653316,
        "nauc_recall_at_100_diff1": -0.097699,
        "nauc_recall_at_1000_max": NaN,
        "nauc_recall_at_1000_std": NaN,
        "nauc_recall_at_1000_diff1": NaN,
        "nauc_precision_at_1_max": 0.309381,
        "nauc_precision_at_1_std": 0.145117,
        "nauc_precision_at_1_diff1": 0.456541,
        "nauc_precision_at_3_max": 0.034943,
        "nauc_precision_at_3_std": 0.003033,
        "nauc_precision_at_3_diff1": -0.085326,
        "nauc_precision_at_5_max": -0.085685,
        "nauc_precision_at_5_std": -0.068284,
        "nauc_precision_at_5_diff1": -0.197866,
        "nauc_precision_at_10_max": -0.088368,
        "nauc_precision_at_10_std": -0.034154,
        "nauc_precision_at_10_diff1": -0.244028,
        "nauc_precision_at_20_max": -0.12091,
        "nauc_precision_at_20_std": -0.02175,
        "nauc_precision_at_20_diff1": -0.293581,
        "nauc_precision_at_100_max": -0.187133,
        "nauc_precision_at_100_std": -0.055328,
        "nauc_precision_at_100_diff1": -0.342628,
        "nauc_precision_at_1000_max": -0.267134,
        "nauc_precision_at_1000_std": -0.136207,
        "nauc_precision_at_1000_diff1": -0.356456,
        "nauc_mrr_at_1_max": 0.309381,
        "nauc_mrr_at_1_std": 0.145117,
        "nauc_mrr_at_1_diff1": 0.456541,
        "nauc_mrr_at_3_max": 0.357617,
        "nauc_mrr_at_3_std": 0.161111,
        "nauc_mrr_at_3_diff1": 0.409161,
        "nauc_mrr_at_5_max": 0.342862,
        "nauc_mrr_at_5_std": 0.154284,
        "nauc_mrr_at_5_diff1": 0.400821,
        "nauc_mrr_at_10_max": 0.343411,
        "nauc_mrr_at_10_std": 0.157741,
        "nauc_mrr_at_10_diff1": 0.396832,
        "nauc_mrr_at_20_max": 0.341879,
        "nauc_mrr_at_20_std": 0.160154,
        "nauc_mrr_at_20_diff1": 0.395927,
        "nauc_mrr_at_100_max": 0.341496,
        "nauc_mrr_at_100_std": 0.160241,
        "nauc_mrr_at_100_diff1": 0.395779,
        "nauc_mrr_at_1000_max": 0.341528,
        "nauc_mrr_at_1000_std": 0.15995,
        "nauc_mrr_at_1000_diff1": 0.396461,
        "cv_recall_at_1": 0.61875,
        "cv_recall_at_3": 0.83125,
        "cv_recall_at_5": 0.9,
        "cv_recall_at_10": 0.925,
        "cv_recall_at_20": 0.9625,
        "cv_recall_at_100": 0.98125,
        "cv_recall_at_1000": 1.0,
        "main_score": 0.6489,
        "hf_subset": "spanish",
        "languages": [
          "spa-Latn"
        ]
      },
      {
        "ndcg_at_1": 0.61875,
        "ndcg_at_3": 0.6232,
        "ndcg_at_5": 0.65091,
        "ndcg_at_10": 0.67914,
        "ndcg_at_20": 0.70268,
        "ndcg_at_100": 0.73679,
        "ndcg_at_1000": 0.74915,
        "map_at_1": 0.37897,
        "map_at_3": 0.5114,
        "map_at_5": 0.55764,
        "map_at_10": 0.59073,
        "map_at_20": 0.60635,
        "map_at_100": 0.61764,
        "map_at_1000": 0.6191,
        "recall_at_1": 0.37897,
        "recall_at_3": 0.58213,
        "recall_at_5": 0.683,
        "recall_at_10": 0.76913,
        "recall_at_20": 0.83194,
        "recall_at_100": 0.94518,
        "recall_at_1000": 1.0,
        "accuracy": 0.37897,
        "precision_at_1": 0.61875,
        "precision_at_3": 0.38542,
        "precision_at_5": 0.2975,
        "precision_at_10": 0.1875,
        "precision_at_20": 0.10969,
        "precision_at_100": 0.02819,
        "precision_at_1000": 0.00322,
        "mrr_at_1": 0.61875,
        "mrr_at_3": 0.705208,
        "mrr_at_5": 0.727083,
        "mrr_at_10": 0.731007,
        "mrr_at_20": 0.731878,
        "mrr_at_100": 0.732838,
        "mrr_at_1000": 0.732892,
        "nauc_ndcg_at_1_max": 0.365843,
        "nauc_ndcg_at_1_std": 0.178173,
        "nauc_ndcg_at_1_diff1": 0.417441,
        "nauc_ndcg_at_3_max": 0.345198,
        "nauc_ndcg_at_3_std": 0.124792,
        "nauc_ndcg_at_3_diff1": 0.355321,
        "nauc_ndcg_at_5_max": 0.360191,
        "nauc_ndcg_at_5_std": 0.143556,
        "nauc_ndcg_at_5_diff1": 0.348824,
        "nauc_ndcg_at_10_max": 0.378845,
        "nauc_ndcg_at_10_std": 0.182095,
        "nauc_ndcg_at_10_diff1": 0.334962,
        "nauc_ndcg_at_20_max": 0.372909,
        "nauc_ndcg_at_20_std": 0.183513,
        "nauc_ndcg_at_20_diff1": 0.320006,
        "nauc_ndcg_at_100_max": 0.364211,
        "nauc_ndcg_at_100_std": 0.184813,
        "nauc_ndcg_at_100_diff1": 0.323086,
        "nauc_ndcg_at_1000_max": 0.350153,
        "nauc_ndcg_at_1000_std": 0.155123,
        "nauc_ndcg_at_1000_diff1": 0.319307,
        "nauc_map_at_1_max": 0.333012,
        "nauc_map_at_1_std": 0.135789,
        "nauc_map_at_1_diff1": 0.557486,
        "nauc_map_at_3_max": 0.343505,
        "nauc_map_at_3_std": 0.132453,
        "nauc_map_at_3_diff1": 0.455266,
        "nauc_map_at_5_max": 0.349814,
        "nauc_map_at_5_std": 0.12679,
        "nauc_map_at_5_diff1": 0.41987,
        "nauc_map_at_10_max": 0.352617,
        "nauc_map_at_10_std": 0.14832,
        "nauc_map_at_10_diff1": 0.384196,
        "nauc_map_at_20_max": 0.35438,
        "nauc_map_at_20_std": 0.150571,
        "nauc_map_at_20_diff1": 0.37111,
        "nauc_map_at_100_max": 0.353107,
        "nauc_map_at_100_std": 0.149537,
        "nauc_map_at_100_diff1": 0.366455,
        "nauc_map_at_1000_max": 0.351465,
        "nauc_map_at_1000_std": 0.146905,
        "nauc_map_at_1000_diff1": 0.365295,
        "nauc_recall_at_1_max": 0.333012,
        "nauc_recall_at_1_std": 0.135789,
        "nauc_recall_at_1_diff1": 0.557486,
        "nauc_recall_at_3_max": 0.348271,
        "nauc_recall_at_3_std": 0.130868,
        "nauc_recall_at_3_diff1": 0.39886,
        "nauc_recall_at_5_max": 0.359392,
        "nauc_recall_at_5_std": 0.151856,
        "nauc_recall_at_5_diff1": 0.295128,
        "nauc_recall_at_10_max": 0.372545,
        "nauc_recall_at_10_std": 0.246611,
        "nauc_recall_at_10_diff1": 0.185275,
        "nauc_recall_at_20_max": 0.356836,
        "nauc_recall_at_20_std": 0.254732,
        "nauc_recall_at_20_diff1": 0.117972,
        "nauc_recall_at_100_max": 0.427647,
        "nauc_recall_at_100_std": 0.589028,
        "nauc_recall_at_100_diff1": 0.15209,
        "nauc_recall_at_1000_max": NaN,
        "nauc_recall_at_1000_std": NaN,
        "nauc_recall_at_1000_diff1": NaN,
        "nauc_precision_at_1_max": 0.365843,
        "nauc_precision_at_1_std": 0.178173,
        "nauc_precision_at_1_diff1": 0.417441,
        "nauc_precision_at_3_max": 0.126807,
        "nauc_precision_at_3_std": 0.055096,
        "nauc_precision_at_3_diff1": -0.133921,
        "nauc_precision_at_5_max": 0.008405,
        "nauc_precision_at_5_std": -0.020849,
        "nauc_precision_at_5_diff1": -0.297492,
        "nauc_precision_at_10_max": -0.042341,
        "nauc_precision_at_10_std": -0.003863,
        "nauc_precision_at_10_diff1": -0.361468,
        "nauc_precision_at_20_max": -0.074369,
        "nauc_precision_at_20_std": -0.016342,
        "nauc_precision_at_20_diff1": -0.381886,
        "nauc_precision_at_100_max": -0.173819,
        "nauc_precision_at_100_std": -0.09737,
        "nauc_precision_at_100_diff1": -0.386198,
        "nauc_precision_at_1000_max": -0.250321,
        "nauc_precision_at_1000_std": -0.188179,
        "nauc_precision_at_1000_diff1": -0.397431,
        "nauc_mrr_at_1_max": 0.365843,
        "nauc_mrr_at_1_std": 0.178173,
        "nauc_mrr_at_1_diff1": 0.417441,
        "nauc_mrr_at_3_max": 0.405747,
        "nauc_mrr_at_3_std": 0.18438,
        "nauc_mrr_at_3_diff1": 0.380872,
        "nauc_mrr_at_5_max": 0.394535,
        "nauc_mrr_at_5_std": 0.189526,
        "nauc_mrr_at_5_diff1": 0.358728,
        "nauc_mrr_at_10_max": 0.388292,
        "nauc_mrr_at_10_std": 0.188692,
        "nauc_mrr_at_10_diff1": 0.357185,
        "nauc_mrr_at_20_max": 0.386416,
        "nauc_mrr_at_20_std": 0.187689,
        "nauc_mrr_at_20_diff1": 0.357345,
        "nauc_mrr_at_100_max": 0.38608,
        "nauc_mrr_at_100_std": 0.187975,
        "nauc_mrr_at_100_diff1": 0.35891,
        "nauc_mrr_at_1000_max": 0.386127,
        "nauc_mrr_at_1000_std": 0.187851,
        "nauc_mrr_at_1000_diff1": 0.359231,
        "cv_recall_at_1": 0.61875,
        "cv_recall_at_3": 0.81875,
        "cv_recall_at_5": 0.9125,
        "cv_recall_at_10": 0.94375,
        "cv_recall_at_20": 0.95625,
        "cv_recall_at_100": 0.9875,
        "cv_recall_at_1000": 1.0,
        "main_score": 0.65091,
        "hf_subset": "german",
        "languages": [
          "deu-Latn"
        ]
      },
      {
        "ndcg_at_1": 0.64375,
        "ndcg_at_3": 0.64382,
        "ndcg_at_5": 0.66814,
        "ndcg_at_10": 0.69869,
        "ndcg_at_20": 0.72264,
        "ndcg_at_100": 0.75559,
        "ndcg_at_1000": 0.76692,
        "map_at_1": 0.40626,
        "map_at_3": 0.53598,
        "map_at_5": 0.57697,
        "map_at_10": 0.61238,
        "map_at_20": 0.6274,
        "map_at_100": 0.63908,
        "map_at_1000": 0.64039,
        "recall_at_1": 0.40626,
        "recall_at_3": 0.60056,
        "recall_at_5": 0.69214,
        "recall_at_10": 0.77996,
        "recall_at_20": 0.84606,
        "recall_at_100": 0.94902,
        "recall_at_1000": 1.0,
        "accuracy": 0.40626,
        "precision_at_1": 0.64375,
        "precision_at_3": 0.3875,
        "precision_at_5": 0.295,
        "precision_at_10": 0.18875,
        "precision_at_20": 0.11031,
        "precision_at_100": 0.0285,
        "precision_at_1000": 0.00322,
        "mrr_at_1": 0.64375,
        "mrr_at_3": 0.733333,
        "mrr_at_5": 0.749271,
        "mrr_at_10": 0.753782,
        "mrr_at_20": 0.75514,
        "mrr_at_100": 0.755681,
        "mrr_at_1000": 0.755734,
        "nauc_ndcg_at_1_max": 0.386547,
        "nauc_ndcg_at_1_std": 0.096946,
        "nauc_ndcg_at_1_diff1": 0.439482,
        "nauc_ndcg_at_3_max": 0.342691,
        "nauc_ndcg_at_3_std": 0.046239,
        "nauc_ndcg_at_3_diff1": 0.423586,
        "nauc_ndcg_at_5_max": 0.377057,
        "nauc_ndcg_at_5_std": 0.080308,
        "nauc_ndcg_at_5_diff1": 0.451917,
        "nauc_ndcg_at_10_max": 0.389992,
        "nauc_ndcg_at_10_std": 0.088704,
        "nauc_ndcg_at_10_diff1": 0.45034,
        "nauc_ndcg_at_20_max": 0.38663,
        "nauc_ndcg_at_20_std": 0.108875,
        "nauc_ndcg_at_20_diff1": 0.424492,
        "nauc_ndcg_at_100_max": 0.38102,
        "nauc_ndcg_at_100_std": 0.106762,
        "nauc_ndcg_at_100_diff1": 0.406678,
        "nauc_ndcg_at_1000_max": 0.358464,
        "nauc_ndcg_at_1000_std": 0.078911,
        "nauc_ndcg_at_1000_diff1": 0.40379,
        "nauc_map_at_1_max": 0.386281,
        "nauc_map_at_1_std": 0.054487,
        "nauc_map_at_1_diff1": 0.534314,
        "nauc_map_at_3_max": 0.364844,
        "nauc_map_at_3_std": 0.05262,
        "nauc_map_at_3_diff1": 0.478618,
        "nauc_map_at_5_max": 0.364301,
        "nauc_map_at_5_std": 0.054077,
        "nauc_map_at_5_diff1": 0.480362,
        "nauc_map_at_10_max": 0.363444,
        "nauc_map_at_10_std": 0.052006,
        "nauc_map_at_10_diff1": 0.460307,
        "nauc_map_at_20_max": 0.367805,
        "nauc_map_at_20_std": 0.06686,
        "nauc_map_at_20_diff1": 0.444294,
        "nauc_map_at_100_max": 0.366338,
        "nauc_map_at_100_std": 0.065835,
        "nauc_map_at_100_diff1": 0.437259,
        "nauc_map_at_1000_max": 0.363887,
        "nauc_map_at_1000_std": 0.063544,
        "nauc_map_at_1000_diff1": 0.436366,
        "nauc_recall_at_1_max": 0.386281,
        "nauc_recall_at_1_std": 0.054487,
        "nauc_recall_at_1_diff1": 0.534314,
        "nauc_recall_at_3_max": 0.36194,
        "nauc_recall_at_3_std": 0.050987,
        "nauc_recall_at_3_diff1": 0.471867,
        "nauc_recall_at_5_max": 0.365678,
        "nauc_recall_at_5_std": 0.08836,
        "nauc_recall_at_5_diff1": 0.473944,
        "nauc_recall_at_10_max": 0.392861,
        "nauc_recall_at_10_std": 0.125953,
        "nauc_recall_at_10_diff1": 0.427261,
        "nauc_recall_at_20_max": 0.380451,
        "nauc_recall_at_20_std": 0.211011,
        "nauc_recall_at_20_diff1": 0.328187,
        "nauc_recall_at_100_max": 0.536727,
        "nauc_recall_at_100_std": 0.506034,
        "nauc_recall_at_100_diff1": 0.219318,
        "nauc_recall_at_1000_max": NaN,
        "nauc_recall_at_1000_std": NaN,
        "nauc_recall_at_1000_diff1": NaN,
        "nauc_precision_at_1_max": 0.386547,
        "nauc_precision_at_1_std": 0.096946,
        "nauc_precision_at_1_diff1": 0.439482,
        "nauc_precision_at_3_max": 0.032956,
        "nauc_precision_at_3_std": 0.024859,
        "nauc_precision_at_3_diff1": -0.071138,
        "nauc_precision_at_5_max": -0.045126,
        "nauc_precision_at_5_std": 0.014709,
        "nauc_precision_at_5_diff1": -0.167865,
        "nauc_precision_at_10_max": -0.106279,
        "nauc_precision_at_10_std": -0.012797,
        "nauc_precision_at_10_diff1": -0.265312,
        "nauc_precision_at_20_max": -0.147017,
        "nauc_precision_at_20_std": 0.001735,
        "nauc_precision_at_20_diff1": -0.334437,
        "nauc_precision_at_100_max": -0.251966,
        "nauc_precision_at_100_std": -0.081089,
        "nauc_precision_at_100_diff1": -0.387468,
        "nauc_precision_at_1000_max": -0.326432,
        "nauc_precision_at_1000_std": -0.1574,
        "nauc_precision_at_1000_diff1": -0.388852,
        "nauc_mrr_at_1_max": 0.386547,
        "nauc_mrr_at_1_std": 0.096946,
        "nauc_mrr_at_1_diff1": 0.439482,
        "nauc_mrr_at_3_max": 0.410116,
        "nauc_mrr_at_3_std": 0.119238,
        "nauc_mrr_at_3_diff1": 0.430578,
        "nauc_mrr_at_5_max": 0.411595,
        "nauc_mrr_at_5_std": 0.125918,
        "nauc_mrr_at_5_diff1": 0.424397,
        "nauc_mrr_at_10_max": 0.408862,
        "nauc_mrr_at_10_std": 0.127447,
        "nauc_mrr_at_10_diff1": 0.420838,
        "nauc_mrr_at_20_max": 0.405701,
        "nauc_mrr_at_20_std": 0.125327,
        "nauc_mrr_at_20_diff1": 0.418986,
        "nauc_mrr_at_100_max": 0.405056,
        "nauc_mrr_at_100_std": 0.125233,
        "nauc_mrr_at_100_diff1": 0.41822,
        "nauc_mrr_at_1000_max": 0.40505,
        "nauc_mrr_at_1000_std": 0.125078,
        "nauc_mrr_at_1000_diff1": 0.418436,
        "cv_recall_at_1": 0.64375,
        "cv_recall_at_3": 0.84375,
        "cv_recall_at_5": 0.9125,
        "cv_recall_at_10": 0.95,
        "cv_recall_at_20": 0.96875,
        "cv_recall_at_100": 0.9875,
        "cv_recall_at_1000": 1.0,
        "main_score": 0.66814,
        "hf_subset": "english",
        "languages": [
          "eng-Latn"
        ]
      }
    ]
  },
  "evaluation_time": 441.3130133152008,
  "kg_co2_emissions": null
}